{
  "seq": 101,
  "id": "PTD-0101",
  "type": "decision",
  "timestamp": "2026-06-22T20:40:00Z",
  "actor": "builder-agent",
  "summary": "Платформа: добавлен поясняющий экран «Как поддержать проект — простыми словами» (platform/app/support/) — зеркало нормативного документа docs/SUPPORT-MODEL.md внутри приложения (тот же приём «экран-зеркало», что «Манифест»↔MANIFESTO, «Конституция»↔CONSTITUTION, «Как фонд принимает решения»↔GOVERNANCE, «Порядок помощи»↔PRIORITIES, «Оплата напрямую»↔ESCROW). Простым языком (правило PTD-0040): поддержка приходит из самой работающей системы, а не отдельной кнопкой-донатом сбоку; почему нет кнопки «Поддержать» с одним кошельком; как пойдут донаты, когда система заработает (общая казна под подписью 3 из 5 хранителей, всё видно в журнале и в блокчейне, расход — только по голосованию); опора на конституцию (5 правил); что значит сейчас (адрес для реальных денег не публикуется, лучшая поддержка — участие); чего фонд не делает (6 рельс); рельс безопасности (TESTNET-first, реальные деньги только после аудита и под общей подписью). Экран-ОБЪЯСНЕНИЕ со ссылкой на полный документ SUPPORT-MODEL.md. Этим закрыта серия экранов-зеркал нормативных документов внутри приложения. Тексты двуязычно RU↔EN в lib/i18n.ts (SupportDict, 26 ключей с обеих сторон), слой текстов отделён от UI, без новых зависимостей (рельса прозрачности); добавлен в постоянное меню шапки после «Всё под подписью». TESTNET-first, реальных денег нет.",
  "refs": [
    "platform/app/support/page.tsx",
    "platform/lib/i18n.ts",
    "platform/components/SiteHeader.tsx",
    "docs/SUPPORT-MODEL.md",
    "INBOX#34"
  ],
  "payload": {},
  "prev_hash": "98bf898e4ada4f23ae67bf327b36f2da21bef74b1d9b3b84429c6a17bcca7936",
  "hash": "dc1fe3019ef925c4e835b03dacf82b294e5c71357005f1935e4ad51143bddd28"
}
